shaudit/__init__.py
shaudit/main.py
shaudit-0.0.1.dist-info/METADATA
shaudit-0.0.1.dist-info/WHEEL
shaudit-0.0.1.dist-info/entry_points.txt
shaudit-0.0.1.dist-info/top_level.txt
shaudit-0.0.1.dist-info/RECORD
