Metadata-Version: 2.2
Name: shaudit
Version: 0.0.1
Summary: Security Headers Audit Tool
Author: invisiber
Classifier: Programming Language :: Python :: 3
Classifier: License :: OSI Approved :: MIT License
Requires-Python: >=3.6
Requires-Dist: argparse
Requires-Dist: requests
Requires-Dist: urllib3
Dynamic: author
Dynamic: classifier
Dynamic: description
Dynamic: description-content-type
Dynamic: requires-dist
Dynamic: requires-python
Dynamic: summary
